mff_pytex/__init__.py
mff_pytex/bib.py
mff_pytex/exceptions.py
mff_pytex/images.py
mff_pytex/packages.py
mff_pytex/structure.py
mff_pytex/tables.py
mff_pytex/utils.py
mff_pytex/examples/example.py
mff_pytex/interface/__init__.py
mff_pytex/interface/interface.py
mff_pytex-0.4.2.dist-info/LICENSE
mff_pytex-0.4.2.dist-info/METADATA
mff_pytex-0.4.2.dist-info/WHEEL
mff_pytex-0.4.2.dist-info/entry_points.txt
mff_pytex-0.4.2.dist-info/top_level.txt
mff_pytex-0.4.2.dist-info/RECORD
