Metadata-Version: 2.1
Name: mff-pytex
Version: 0.4.2
Summary: MFF PyTeX is a framework for writing tex documents in python.
Home-page: https://github.com/ondrachwiedziuk/mff_pytex
Author: Ondřej Chwiedziuk
Author-email: ondrachwiedziuk@gmail.com
Keywords: mff_pytex
Classifier: License :: OSI Approved :: MIT License
Classifier: Operating System :: POSIX :: Linux
Classifier: Programming Language :: Python :: 3
Classifier: Programming Language :: Python :: 3.7
Classifier: Programming Language :: Python :: 3.8
Classifier: Programming Language :: Python :: 3.9
Classifier: Programming Language :: Python :: 3.10
Requires-Python: >=3.10
License-File: LICENSE
Requires-Dist: click (==8.1.3)
